{"name":"tutorial","created":"2017-03-28T23:31:11.841Z","intents":[{"intent":"consulta_saldo_conta","created":"2017-03-28T23:55:10.922Z","updated":"2017-03-28T23:55:10.922Z","examples":[{"text":"o que eu tenho na conta","created":"2017-03-28T23:55:10.922Z","updated":"2017-03-28T23:55:10.922Z"},{"text":"qual o saldo da minha conta","created":"2017-03-28T23:55:10.922Z","updated":"2017-03-28T23:55:10.922Z"},{"text":"quanto eu tenho na conta","created":"2017-03-28T23:55:10.922Z","updated":"2017-03-28T23:55:10.922Z"},{"text":"quero consultar o saldo da minha conta","created":"2017-03-28T23:55:10.922Z","updated":"2017-03-28T23:55:10.922Z"},{"text":"tenho algo na conta","created":"2017-03-28T23:55:10.922Z","updated":"2017-03-28T23:55:10.922Z"}],"description":null},{"intent":"saudacao","created":"2017-03-28T23:54:14.540Z","updated":"2017-03-28T23:54:14.540Z","examples":[{"text":"boa noite","created":"2017-03-28T23:54:14.540Z","updated":"2017-03-28T23:54:14.540Z"},{"text":"boa tarde","created":"2017-03-28T23:54:14.540Z","updated":"2017-03-28T23:54:14.540Z"},{"text":"bom dia","created":"2017-03-28T23:54:14.540Z","updated":"2017-03-28T23:54:14.540Z"},{"text":"ola","created":"2017-03-28T23:54:14.540Z","updated":"2017-03-28T23:54:14.540Z"},{"text":"olá","created":"2017-03-28T23:54:14.540Z","updated":"2017-03-28T23:54:14.540Z"}],"description":null}],"updated":"2017-04-09T06:37:53.196Z","entities":[{"entity":"tipo_conta","values":[{"value":"conta corrente","created":"2017-03-29T00:04:54.555Z","updated":"2017-03-29T00:04:54.555Z","metadata":null,"synonyms":["cc"]},{"value":"conta poupança","created":"2017-03-29T00:04:54.555Z","updated":"2017-03-29T00:04:54.555Z","metadata":null,"synonyms":["conta poupanca","cp"]}],"created":"2017-03-29T00:04:54.555Z","updated":"2017-03-29T00:04:54.555Z","metadata":null,"description":null}],"language":"pt-br","metadata":{"runtime_version":"2017-02-03"},"description":"","dialog_nodes":[{"go_to":null,"output":{"text":{"values":["A qual tipo de conta você se refere, conta corrente ou conta poupança?"],"selection_policy":"sequential"}},"parent":null,"context":{"contador":0},"created":"2017-03-29T00:52:27.064Z","updated":"2017-04-09T06:09:45.865Z","metadata":null,"conditions":"#consulta_saldo_conta","description":null,"dialog_node":"node_4_1490748746358","previous_sibling":"node_3_1490748585377"},{"go_to":null,"output":{"text":{"values":["Bem vindo ao conversation!"],"selection_policy":"sequential"}},"parent":null,"context":null,"created":"2017-03-29T00:14:19.447Z","updated":"2017-03-29T00:46:30.305Z","metadata":null,"conditions":"conversation_start","description":null,"dialog_node":"node_1_1490746459235","previous_sibling":null},{"go_to":null,"output":{"text":{"values":["Desculpe, não entendi. me informe novamente a qual tipo de conta deseja consultar o saldo, conta corrente ou conta poupança? Você errou <? context.contador ?> vez(es)."],"selection_policy":"sequential"}},"parent":"node_4_1490748746358","context":{"contador":"<? context.contador + 1 ?>"},"created":"2017-04-09T05:37:14.934Z","updated":"2017-04-09T06:30:36.123Z","metadata":null,"conditions":"anything_else","description":null,"dialog_node":"node_1_1491716234264","previous_sibling":"node_3_1491719440826"},{"go_to":null,"output":{"text":{"values":["Desculpe, não entendi o que você falou."],"selection_policy":"sequential"}},"parent":null,"context":null,"created":"2017-03-29T00:19:35.804Z","updated":"2017-03-29T00:47:41.743Z","metadata":null,"conditions":"anything_else","description":null,"dialog_node":"node_2_1490746775606","previous_sibling":"node_4_1490748746358"},{"go_to":null,"output":{"text":{"values":["Desculpe, você errou mais de duas vezes. Tente novamente"],"selection_policy":"sequential"}},"parent":"node_4_1490748746358","context":null,"created":"2017-04-09T06:30:41.053Z","updated":"2017-04-09T06:37:53.196Z","metadata":null,"conditions":"context.contador >= 2","description":null,"dialog_node":"node_3_1491719440826","previous_sibling":"node_6_1490749019091"},{"go_to":null,"output":{"text":{"values":["Olá para você também."],"selection_policy":"sequential"}},"parent":null,"context":null,"created":"2017-03-29T00:49:45.896Z","updated":"2017-03-29T00:51:39.001Z","metadata":null,"conditions":"#saudacao","description":null,"dialog_node":"node_3_1490748585377","previous_sibling":"node_1_1490746459235"},{"go_to":null,"output":{"text":{"values":["Você possui 10 reais na sua conta corrente."],"selection_policy":"sequential"}},"parent":"node_4_1490748746358","context":null,"created":"2017-03-29T00:55:06.322Z","updated":"2017-04-09T05:42:09.339Z","metadata":null,"conditions":"@tipo_conta:(conta corrente)","description":null,"dialog_node":"node_5_1490748905536","previous_sibling":null},{"go_to":null,"output":{"text":{"values":["Você possui 5 reais na sua conta poupança."],"selection_policy":"sequential"}},"parent":"node_4_1490748746358","context":null,"created":"2017-03-29T00:56:59.768Z","updated":"2017-04-09T06:32:13.538Z","metadata":null,"conditions":"@tipo_conta:(conta poupança)","description":null,"dialog_node":"node_6_1490749019091","previous_sibling":"node_5_1490748905536"},{"go_to":{"return":null,"selector":"condition","dialog_node":"node_5_1490748905536"},"output":{},"parent":"node_1_1491716234264","context":null,"created":"2017-04-09T05:42:09.793Z","updated":"2017-04-09T05:50:25.504Z","metadata":null,"conditions":"true","description":null,"dialog_node":"node_2_1491716529550","previous_sibling":null}],"workspace_id":"1cfe14b8-5c08-449e-a0a8-4899a63ad0d3","counterexamples":[]}